discordyml/__init__.py
discordyml-1.0.1.dist-info/WHEEL
discordyml-1.0.1.dist-info/METADATA
discordyml-1.0.1.dist-info/RECORD
