Metadata-Version: 2.1
Name: discordyml
Version: 1.0.1
Summary: An easy (but probably inefficient) library to assign data to discord users and guilds using a small subset of YAML
Author: Umar Sharief
Author-email: umar.sharief04@gmail.com
Requires-Python: >=3.8,<4.0
Classifier: Programming Language :: Python :: 3
Classifier: Programming Language :: Python :: 3.8
Classifier: Programming Language :: Python :: 3.9
Classifier: Programming Language :: Python :: 3.10
